README.md
setup.py
fc_tunnel/__init__.py
fc_tunnel/app.py
fc_tunnel.egg-info/PKG-INFO
fc_tunnel.egg-info/SOURCES.txt
fc_tunnel.egg-info/dependency_links.txt
fc_tunnel.egg-info/entry_points.txt
fc_tunnel.egg-info/requires.txt
fc_tunnel.egg-info/top_level.txt