Metadata-Version: 2.1
Name: fc-tunnel
Version: 0.0.7
Summary: Use FC to open up the tunnel between the local and Alibaba Cloud vpc network
Home-page: https://www.aliyun.com/product/fc
Author: xiliu
Author-email: ls_huster@163.com
License: UNKNOWN
Platform: UNKNOWN
Classifier: Development Status :: 5 - Production/Stable
Classifier: Intended Audience :: Developers
Classifier: License :: OSI Approved :: MIT License
Classifier: Operating System :: OS Independent
Classifier: Programming Language :: Python
Classifier: Programming Language :: Python :: 3.4
Classifier: Programming Language :: Python :: 3.5
Classifier: Programming Language :: Python :: 3.6
Classifier: Programming Language :: Python :: 3.7
Classifier: Programming Language :: Python :: 3.8
Classifier: Programming Language :: Python :: 3.9
